system_settings_service/__init__.py
system_settings_service/common_pb2.py
system_settings_service/common_pb2_grpc.py
system_settings_service/grpc_client.py
system_settings_service/models.py
system_settings_service/systemSettingsService_pb2.py
system_settings_service/systemSettingsService_pb2_grpc.py
longleding_system_settings_service_sdk-0.1.5.dist-info/LICENSE
longleding_system_settings_service_sdk-0.1.5.dist-info/METADATA
longleding_system_settings_service_sdk-0.1.5.dist-info/WHEEL
longleding_system_settings_service_sdk-0.1.5.dist-info/top_level.txt
longleding_system_settings_service_sdk-0.1.5.dist-info/RECORD
