Metadata-Version: 2.1
Name: longleding-system-settings-service-sdk
Version: 0.1.5
Summary: Longleding System Settings Service SDK
Home-page: https://git.emhub.top/em/system-settings-service
Author: Shi Ran
Author-email: ran.shi@longleding.com
License: UNKNOWN
Platform: UNKNOWN
Classifier: Programming Language :: Python :: 3
Classifier: Topic :: System :: Logging
Requires-Python: >=3.6
